shioaji/__init__.py
shioaji/_version.py
shioaji/account.py
shioaji/backend/__init__.py
shioaji/backend/constant.cp311-win_amd64.pyd
shioaji/backend/error.cp311-win_amd64.pyd
shioaji/backend/solace/__init__.py
shioaji/backend/solace/api.cp311-win_amd64.pyd
shioaji/backend/solace/bidask.cp311-win_amd64.pyd
shioaji/backend/solace/quote.cp311-win_amd64.pyd
shioaji/backend/solace/tick.cp311-win_amd64.pyd
shioaji/backend/solace/utils.cp311-win_amd64.pyd
shioaji/backend/utils.cp311-win_amd64.pyd
shioaji/base.py
shioaji/common.py
shioaji/config.py
shioaji/constant.py
shioaji/contracts.py
shioaji/data.py
shioaji/error.py
shioaji/order.py
shioaji/orderprops.py
shioaji/position.py
shioaji/reserve.py
shioaji/shioaji.py
shioaji/stream_data_type.py
shioaji/utils.py
shioaji-1.3.1.dist-info/METADATA
shioaji-1.3.1.dist-info/WHEEL
shioaji-1.3.1.dist-info/entry_points.txt
shioaji-1.3.1.dist-info/RECORD
