Metadata-Version: 2.1
Name: shioaji
Version: 1.3.1
Summary: Sinopac All New Trading Api.
Author-Email: yvictor <yvictor3141@gmail.com>
Classifier: Development Status :: 5 - Production/Stable
Classifier: Environment :: Console
Classifier: Intended Audience :: Developers
Classifier: Operating System :: POSIX
Classifier: Operating System :: MacOS
Classifier: Operating System :: Unix
Classifier: Operating System :: Microsoft :: Windows
Classifier: Programming Language :: Python :: 3
Classifier: Programming Language :: Python :: 3 :: Only
Classifier: Programming Language :: Python :: 3.7
Classifier: Programming Language :: Python :: 3.8
Classifier: Programming Language :: Python :: 3.9
Classifier: Programming Language :: Python :: 3.10
Classifier: Programming Language :: Python :: 3.11
Classifier: Programming Language :: Python :: 3.12
Classifier: Programming Language :: Python :: 3.13
Classifier: Programming Language :: Python :: 3.14
Classifier: Programming Language :: Python :: Implementation :: CPython
Classifier: Programming Language :: Cython
Classifier: Programming Language :: C++
Classifier: Topic :: Software Development :: Libraries :: Python Modules
Classifier: Topic :: Office/Business :: Financial :: Investment
Project-URL: Homepage, https://github.com/Sinotrade/Shioaji
Requires-Python: >=3.7
Requires-Dist: base58
Requires-Dist: filelock<4.0.0,>=3.4.1
Requires-Dist: importlib-metadata
Requires-Dist: loguru<=0.7.3,>=0.6.0
Requires-Dist: pydantic<=2.12.3,>=1.0.0
Requires-Dist: pynacl>=1.3.0
Requires-Dist: pyrsca
Requires-Dist: pysolace>=0.9.53
Requires-Dist: requests
Requires-Dist: sentry-sdk>=1.5.12
Requires-Dist: typing-extensions
Requires-Dist: xxhash
Requires-Dist: ciso8601>=2.1.3; extra == "speed"
Requires-Dist: based58>=0.1.1; extra == "speed"
Provides-Extra: speed
